MANIFEST.in
README
setup.py
Flask_Jasmine.egg-info/PKG-INFO
Flask_Jasmine.egg-info/SOURCES.txt
Flask_Jasmine.egg-info/dependency_links.txt
Flask_Jasmine.egg-info/not-zip-safe
Flask_Jasmine.egg-info/requires.txt
Flask_Jasmine.egg-info/top_level.txt
flask_jasmine/__init__.py
flask_jasmine/jasmine.py
flask_jasmine/static/Flask-Jasmine.png
flask_jasmine/static/jasmine/MIT.LICENSE
flask_jasmine/static/jasmine/jasmine-html.js
flask_jasmine/static/jasmine/jasmine.css
flask_jasmine/static/jasmine/jasmine.js
flask_jasmine/static/jasmine/jasmine_favicon.png
flask_jasmine/templates/runner.html