Metadata-Version: 1.0
Name: Flask-Jasmine
Version: 1.1
Summary: Execution of Jasmine JavaScript tests within Flask
Home-page: https://github.com/joymax/flask-jasmine
Author: Maksym Klymyshyn
Author-email: klymyshyn@gmail.com
License: BSD
Platform: any
Classifier: Environment :: Web Environment
Classifier: Intended Audience :: Developers
Classifier: License :: OSI Approved :: BSD License
Classifier: Operating System :: OS Independent
Classifier: Programming Language :: Python
Classifier: Topic :: Internet :: WWW/HTTP :: Dynamic Content
Classifier: Topic :: Software Development :: Libraries :: Python Modules
